[
  {
    "char": "0",
    "filename": "0.png",
    "url": "https://stafaz.sgp1.digitaloceanspaces.com/pattern/builtin/image-ickjgim7.png"
  },
  {
    "char": "1",
    "filename": "1.png",
    "url": "https://stafaz.sgp1.digitaloceanspaces.com/pattern/builtin/image-96qqimwx.png"
  },
  {
    "char": "2",
    "filename": "2.png",
    "url": "https://stafaz.sgp1.digitaloceanspaces.com/pattern/builtin/image-qz9x8li3.png"
  },
  {
    "char": "3",
    "filename": "3.png",
    "url": "https://stafaz.sgp1.digitaloceanspaces.com/pattern/builtin/image-alb643x6.png"
  },
  {
    "char": "4",
    "filename": "4.png",
    "url": "https://stafaz.sgp1.digitaloceanspaces.com/pattern/builtin/image-so07rfgn.png"
  },
  {
    "char": "5",
    "filename": "5.png",
    "url": "https://stafaz.sgp1.digitaloceanspaces.com/pattern/builtin/image-nkix577q.png"
  },
  {
    "char": "6",
    "filename": "6.png",
    "url": "https://stafaz.sgp1.digitaloceanspaces.com/pattern/builtin/image-yfyleler.png"
  },
  {
    "char": "7",
    "filename": "7.png",
    "url": "https://stafaz.sgp1.digitaloceanspaces.com/pattern/builtin/image-rqw10tiy.png"
  },
  {
    "char": "8",
    "filename": "8.png",
    "url": "https://stafaz.sgp1.digitaloceanspaces.com/pattern/builtin/image-mt0lthad.png"
  },
  {
    "char": "9",
    "filename": "9.png",
    "url": "https://stafaz.sgp1.digitaloceanspaces.com/pattern/builtin/image-euj5r3dg.png"
  },
  {
    "char": "A",
    "filename": "A.png",
    "url": "https://stafaz.sgp1.digitaloceanspaces.com/pattern/builtin/image-z1o69dmm.png"
  },
  {
    "char": "B",
    "filename": "B.png",
    "url": "https://stafaz.sgp1.digitaloceanspaces.com/pattern/builtin/image-efybtmtf.png"
  },
  {
    "char": "C",
    "filename": "C.png",
    "url": "https://stafaz.sgp1.digitaloceanspaces.com/pattern/builtin/image-i97up4ry.png"
  },
  {
    "char": "D",
    "filename": "D.png",
    "url": "https://stafaz.sgp1.digitaloceanspaces.com/pattern/builtin/image-8bcej654.png"
  },
  {
    "char": "E",
    "filename": "E.png",
    "url": "https://stafaz.sgp1.digitaloceanspaces.com/pattern/builtin/image-zbxmo93h.png"
  },
  {
    "char": "F",
    "filename": "F.png",
    "url": "https://stafaz.sgp1.digitaloceanspaces.com/pattern/builtin/image-goallyna.png"
  },
  {
    "char": "G",
    "filename": "G.png",
    "url": "https://stafaz.sgp1.digitaloceanspaces.com/pattern/builtin/image-noezmpgo.png"
  },
  {
    "char": "H",
    "filename": "H.png",
    "url": "https://stafaz.sgp1.digitaloceanspaces.com/pattern/builtin/image-9qmn1nez.png"
  },
  {
    "char": "I",
    "filename": "I.png",
    "url": "https://stafaz.sgp1.digitaloceanspaces.com/pattern/builtin/image-ije2tx77.png"
  },
  {
    "char": "J",
    "filename": "J.png",
    "url": "https://stafaz.sgp1.digitaloceanspaces.com/pattern/builtin/image-kpf82m9e.png"
  },
  {
    "char": "K",
    "filename": "K.png",
    "url": "https://stafaz.sgp1.digitaloceanspaces.com/pattern/builtin/image-x7gju23d.png"
  },
  {
    "char": "L",
    "filename": "L.png",
    "url": "https://stafaz.sgp1.digitaloceanspaces.com/pattern/builtin/image-5yf337e4.png"
  },
  {
    "char": "M",
    "filename": "M.png",
    "url": "https://stafaz.sgp1.digitaloceanspaces.com/pattern/builtin/image-2yl5kfay.png"
  },
  {
    "char": "N",
    "filename": "N.png",
    "url": "https://stafaz.sgp1.digitaloceanspaces.com/pattern/builtin/image-dycmz113.png"
  },
  {
    "char": "O",
    "filename": "O.png",
    "url": "https://stafaz.sgp1.digitaloceanspaces.com/pattern/builtin/image-b9dqzkk1.png"
  },
  {
    "char": "P",
    "filename": "P.png",
    "url": "https://stafaz.sgp1.digitaloceanspaces.com/pattern/builtin/image-4z98u5dj.png"
  },
  {
    "char": "Q",
    "filename": "Q.png",
    "url": "https://stafaz.sgp1.digitaloceanspaces.com/pattern/builtin/image-dqt5oxdh.png"
  },
  {
    "char": "R",
    "filename": "R.png",
    "url": "https://stafaz.sgp1.digitaloceanspaces.com/pattern/builtin/image-bpnvdcer.png"
  },
  {
    "char": "S",
    "filename": "S.png",
    "url": "https://stafaz.sgp1.digitaloceanspaces.com/pattern/builtin/image-1ppy9nls.png"
  },
  {
    "char": "T",
    "filename": "T.png",
    "url": "https://stafaz.sgp1.digitaloceanspaces.com/pattern/builtin/image-0sye71sy.png"
  },
  {
    "char": "U",
    "filename": "U.png",
    "url": "https://stafaz.sgp1.digitaloceanspaces.com/pattern/builtin/image-za8ibwl8.png"
  },
  {
    "char": "V",
    "filename": "V.png",
    "url": "https://stafaz.sgp1.digitaloceanspaces.com/pattern/builtin/image-kzevhpob.png"
  },
  {
    "char": "W",
    "filename": "W.png",
    "url": "https://stafaz.sgp1.digitaloceanspaces.com/pattern/builtin/image-dly5s83h.png"
  },
  {
    "char": "X",
    "filename": "X.png",
    "url": "https://stafaz.sgp1.digitaloceanspaces.com/pattern/builtin/image-rqzga613.png"
  },
  {
    "char": "Y",
    "filename": "Y.png",
    "url": "https://stafaz.sgp1.digitaloceanspaces.com/pattern/builtin/image-9miavlei.png"
  },
  {
    "char": "Z",
    "filename": "Z.png",
    "url": "https://stafaz.sgp1.digitaloceanspaces.com/pattern/builtin/image-pn3p62sl.png"
  }
]